ruia_pyppeteer/__init__.py
ruia_pyppeteer/request.py
ruia_pyppeteer/response.py
ruia_pyppeteer/spider.py
ruia_pyppeteer-0.0.7.dist-info/LICENSE
ruia_pyppeteer-0.0.7.dist-info/METADATA
ruia_pyppeteer-0.0.7.dist-info/WHEEL
ruia_pyppeteer-0.0.7.dist-info/top_level.txt
ruia_pyppeteer-0.0.7.dist-info/RECORD
