Metadata-Version: 2.1
Name: ruia-pyppeteer
Version: 0.0.7
Summary: ruia_pyppeteer - A Ruia plugin for loading javascript - pyppeteer.
Home-page: https://github.com/ruia-plugins/ruia-pyppeteer
Author: Howie Hu
Author-email: xiaozizayang@gmail.com
License: MIT
Project-URL: Documentation, https://github.com/python-ruia/ruia-pyppeteer
Project-URL: Source, https://github.com/python-ruia/ruia-pyppeteer
Platform: UNKNOWN
Classifier: Intended Audience :: Developers
Classifier: License :: OSI Approved :: MIT License
Classifier: Programming Language :: Python :: 3.6
Classifier: Programming Language :: Python :: 3.7
Classifier: Topic :: Software Development :: Libraries :: Python Modules
Requires-Dist: ruia (>=0.6.7)
Requires-Dist: pyppeteer
